codehutt/__init__.py
codehutt/codehutt.py
codehutt/helper_scripts.py
codehutt/test.py
codehutt-0.0.0.dist-info/LICENSE
codehutt-0.0.0.dist-info/METADATA
codehutt-0.0.0.dist-info/WHEEL
codehutt-0.0.0.dist-info/top_level.txt
codehutt-0.0.0.dist-info/RECORD
